lograptor/__init__.py
lograptor/__main__.py
lograptor/api.py
lograptor/application.py
lograptor/cache.py
lograptor/channels.py
lograptor/confparsers.py
lograptor/core.py
lograptor/dispatchers.py
lograptor/exceptions.py
lograptor/filemap.py
lograptor/info.py
lograptor/logparsers.py
lograptor/matcher.py
lograptor/report.py
lograptor/timedate.py
lograptor/tui.py
lograptor/utils.py
lograptor/config/report_template.html
lograptor/config/report_template.txt
lograptor/config/conf.d/asa.conf
lograptor/config/conf.d/barracuda.conf
lograptor/config/conf.d/crond.conf
lograptor/config/conf.d/dovecot.conf
lograptor/config/conf.d/ntpd.conf
lograptor/config/conf.d/postfix.conf
lograptor/config/conf.d/sshd.conf
lograptor-1.3.0.data/data/share/doc/lograptor/LICENSE
lograptor-1.3.0.data/data/share/doc/lograptor/README.rst
lograptor-1.3.0.data/data/share/doc/lograptor/lograptor.pdf
lograptor-1.3.0.data/data/share/man/man5/lograptor-apps.5.gz
lograptor-1.3.0.data/data/share/man/man5/lograptor.conf.5.gz
lograptor-1.3.0.data/data/share/man/man8/lograptor-examples.8.gz
lograptor-1.3.0.data/data/share/man/man8/lograptor.8.gz
lograptor-1.3.0.dist-info/LICENSE
lograptor-1.3.0.dist-info/METADATA
lograptor-1.3.0.dist-info/WHEEL
lograptor-1.3.0.dist-info/entry_points.txt
lograptor-1.3.0.dist-info/top_level.txt
lograptor-1.3.0.dist-info/RECORD
