Metadata-Version: 2.1
Name: lograptor
Version: 1.3.0
Summary: Command-line utility for processing log files.
Home-page: https://github.com/brunato/lograptor
Author: Davide Brunato
Author-email: brunato@sissa.it
Maintainer: Davide Brunato
License: LGPLv2.1+
Platform: UNKNOWN
Classifier: Development Status :: 5 - Production/Stable
Classifier: Environment :: Console
Classifier: Intended Audience :: System Administrators
Classifier: Intended Audience :: Developers
Classifier: License :: OSI Approved :: GNU Lesser General Public License v2 or later (LGPLv2+)
Classifier: Operating System :: POSIX :: Linux
Classifier: Programming Language :: Python
Classifier: Programming Language :: Python :: 3
Classifier: Programming Language :: Python :: 3.5
Classifier: Programming Language :: Python :: 3.6
Classifier: Programming Language :: Python :: 3.7
Classifier: Programming Language :: Python :: 3.8
Classifier: Programming Language :: Python :: 3.9
Classifier: Topic :: Internet :: Log Analysis
Classifier: Topic :: System :: Systems Administration
Classifier: Topic :: Text Processing :: Filters
Classifier: Topic :: Utilities
Requires: python (>=3.6)
